hlk_dio16/__init__.py
hlk_dio16/const.py
hlk_dio16/protocol.py
hlk_dio16/util.py
hlk_dio16/tools/info.py
hlk_dio16-0.0.1.dist-info/LICENSE
hlk_dio16-0.0.1.dist-info/METADATA
hlk_dio16-0.0.1.dist-info/WHEEL
hlk_dio16-0.0.1.dist-info/top_level.txt
hlk_dio16-0.0.1.dist-info/RECORD
