Metadata-Version: 2.1
Name: hlk-dio16
Version: 0.0.1
Summary: Python client for HLK-DIO16
Home-page: https://github.com/jameshilliard/hlk-dio16
Author: James Hilliard
Author-email: james.hilliard1@gmail.com
License: MIT
Platform: UNKNOWN
